goldenmask/.goldenmaskignore
goldenmask/__init__.py
goldenmask/__main__.py
goldenmask/cli.py
goldenmask/exceptions.py
goldenmask/protect.py
goldenmask/utils.py
goldenmask-0.2.1.dist-info/entry_points.txt
goldenmask-0.2.1.dist-info/LICENSE
goldenmask-0.2.1.dist-info/WHEEL
goldenmask-0.2.1.dist-info/METADATA
goldenmask-0.2.1.dist-info/RECORD
